biofits
