Metadata-Version: 1.1
Name: biofits
Version: 0.24
Summary: Common biochemical data fitting functions
Home-page: https://github.com/jimrybarski/biofits
Author: Jim Rybarski
Author-email: jim@rybarski.com
License: UNKNOWN
Download-URL: https://github.com/jimrybarski/biofits/tarball/0.24
Keywords: biology,biochemistry,kinetics,fitting
Platform: UNKNOWN
Classifier: Development Status :: 4 - Beta
Classifier: Intended Audience :: Science/Research
Classifier: License :: Freely Distributable
Classifier: License :: OSI Approved :: MIT License
Classifier: Programming Language :: Python :: 2
Classifier: Programming Language :: Python :: 3
